bayRing/NR_waveforms.py
bayRing/QNM_utils.py
bayRing/__init__.py
bayRing/bayRing.py
bayRing/inference.py
bayRing/initialise.py
bayRing/postprocess.py
bayRing/template_waveforms.py
bayRing/utils.py
bayRing/waveform_utils.py
bayRing-1.0.0.dist-info/AUTHORS.md
bayRing-1.0.0.dist-info/LICENSE
bayRing-1.0.0.dist-info/METADATA
bayRing-1.0.0.dist-info/WHEEL
bayRing-1.0.0.dist-info/entry_points.txt
bayRing-1.0.0.dist-info/top_level.txt
bayRing-1.0.0.dist-info/RECORD
